<?xml version="1.0" encoding="utf-8"?>
<Race xmlns:xsd="http://www.w3.org/2001/XMLSchema" xmlns:xsi="http://www.w3.org/2001/XMLSchema-instance">
  <Checkpoints>
    <Vector3>
      <X>1160.56274</X>
      <Y>20.9319019</Y>
      <Z>80.85782</Z>
    </Vector3>
    <Vector3>
      <X>1235.91589</X>
      <Y>141.468353</Y>
      <Z>80.85665</Z>
    </Vector3>
    <Vector3>
      <X>1175.565</X>
      <Y>273.590851</Y>
      <Z>80.9165039</Z>
    </Vector3>
    <Vector3>
      <X>1115.66125</X>
      <Y>190.942886</Y>
      <Z>80.84186</Z>
    </Vector3>
    <Vector3>
      <X>1047.93958</X>
      <Y>82.99283</Y>
      <Z>80.845726</Z>
    </Vector3>
    <Vector3>
      <X>1001.26593</X>
      <Y>-60.0745239</Y>
      <Z>80.92738</Z>
    </Vector3>
    <Vector3>
      <X>1117.72021</X>
      <Y>-47.8155632</Y>
      <Z>80.85484</Z>
    </Vector3>
  </Checkpoints>
  <SpawnPoints>
    <SpawnPoint>
      <Position>
        <X>1103.71582</X>
        <Y>-62.06671</Y>
        <Z>81.4578</Z>
      </Position>
      <Heading>-34.757412</Heading>
    </SpawnPoint>
    <SpawnPoint>
      <Position>
        <X>1106.76306</X>
        <Y>-64.03043</Y>
        <Z>81.45044</Z>
      </Position>
      <Heading>-34.6889839</Heading>
    </SpawnPoint>
    <SpawnPoint>
      <Position>
        <X>1100.38892</X>
        <Y>-60.0690575</Y>
        <Z>81.4714661</Z>
      </Position>
      <Heading>-31.8874264</Heading>
    </SpawnPoint>
    <SpawnPoint>
      <Position>
        <X>1095.77124</X>
        <Y>-66.30756</Y>
        <Z>81.79705</Z>
      </Position>
      <Heading>-34.4769859</Heading>
    </SpawnPoint>
    <SpawnPoint>
      <Position>
        <X>1112.479</X>
        <Y>-68.47611</Y>
        <Z>81.27909</Z>
      </Position>
      <Heading>-37.0348625</Heading>
    </SpawnPoint>
    <SpawnPoint>
      <Position>
        <X>1109.48743</X>
        <Y>-66.36598</Y>
        <Z>81.30968</Z>
      </Position>
      <Heading>-33.96431</Heading>
    </SpawnPoint>
    <SpawnPoint>
      <Position>
        <X>1098.8606</X>
        <Y>-68.4730453</Y>
        <Z>81.60448</Z>
      </Position>
      <Heading>-37.5797348</Heading>
    </SpawnPoint>
    <SpawnPoint>
      <Position>
        <X>1101.70093</X>
        <Y>-70.68763</Y>
        <Z>81.48904</Z>
      </Position>
      <Heading>-37.44016</Heading>
    </SpawnPoint>
    <SpawnPoint>
      <Position>
        <X>1104.89148</X>
        <Y>-72.92509</Y>
        <Z>81.31642</Z>
      </Position>
      <Heading>-35.05371</Heading>
    </SpawnPoint>
    <SpawnPoint>
      <Position>
        <X>1107.92651</X>
        <Y>-75.29432</Y>
        <Z>81.30769</Z>
      </Position>
      <Heading>-34.9172325</Heading>
    </SpawnPoint>
    <SpawnPoint>
      <Position>
        <X>1104.45459</X>
        <Y>-53.687767</Y>
        <Z>81.47105</Z>
      </Position>
      <Heading>-31.0003929</Heading>
    </SpawnPoint>
    <SpawnPoint>
      <Position>
        <X>1108.02551</X>
        <Y>-55.4795227</Y>
        <Z>81.45255</Z>
      </Position>
      <Heading>-32.8602448</Heading>
    </SpawnPoint>
    <SpawnPoint>
      <Position>
        <X>1111.25488</X>
        <Y>-57.6763077</Y>
        <Z>81.44095</Z>
      </Position>
      <Heading>-32.28564</Heading>
    </SpawnPoint>
    <SpawnPoint>
      <Position>
        <X>1114.77417</X>
        <Y>-60.17069</Y>
        <Z>81.33795</Z>
      </Position>
      <Heading>-31.3790455</Heading>
    </SpawnPoint>
    <SpawnPoint>
      <Position>
        <X>1117.83569</X>
        <Y>-62.31517</Y>
        <Z>81.35315</Z>
      </Position>
      <Heading>-32.86768</Heading>
    </SpawnPoint>
    <SpawnPoint>
      <Position>
        <X>1109.168</X>
        <Y>-46.7197075</Y>
        <Z>81.4618759</Z>
      </Position>
      <Heading>-31.8592453</Heading>
    </SpawnPoint>
    <SpawnPoint>
      <Position>
        <X>1112.51038</X>
        <Y>-48.610157</Y>
        <Z>81.38757</Z>
      </Position>
      <Heading>-30.6347084</Heading>
    </SpawnPoint>
    <SpawnPoint>
      <Position>
        <X>1115.69116</X>
        <Y>-50.5663948</Y>
        <Z>81.09194</Z>
      </Position>
      <Heading>-30.5668259</Heading>
    </SpawnPoint>
    <SpawnPoint>
      <Position>
        <X>1119.04712</X>
        <Y>-52.9835129</Y>
        <Z>81.49846</Z>
      </Position>
      <Heading>-32.9611969</Heading>
    </SpawnPoint>
    <SpawnPoint>
      <Position>
        <X>1122.11084</X>
        <Y>-55.1567345</Y>
        <Z>81.5838852</Z>
      </Position>
      <Heading>-31.8600273</Heading>
    </SpawnPoint>
    <SpawnPoint>
      <Position>
        <X>1113.44336</X>
        <Y>-40.1292953</Y>
        <Z>81.5844</Z>
      </Position>
      <Heading>-33.55547</Heading>
    </SpawnPoint>
    <SpawnPoint>
      <Position>
        <X>1123.02539</X>
        <Y>-46.32226</Y>
        <Z>81.14615</Z>
      </Position>
      <Heading>-31.7881737</Heading>
    </SpawnPoint>
    <SpawnPoint>
      <Position>
        <X>1125.9386</X>
        <Y>-48.8405724</Y>
        <Z>81.57804</Z>
      </Position>
      <Heading>-32.8524857</Heading>
    </SpawnPoint>
    <SpawnPoint>
      <Position>
        <X>1116.41675</X>
        <Y>-42.17691</Y>
        <Z>81.265</Z>
      </Position>
      <Heading>-31.3621712</Heading>
    </SpawnPoint>
    <SpawnPoint>
      <Position>
        <X>1119.44849</X>
        <Y>-44.459713</Y>
        <Z>81.44235</Z>
      </Position>
      <Heading>-33.34137</Heading>
    </SpawnPoint>
  </SpawnPoints>
  <AvailableVehicles>
    <VehicleHash>Stalion2</VehicleHash>
    <VehicleHash>Gauntlet2</VehicleHash>
    <VehicleHash>Dominator2</VehicleHash>
    <VehicleHash>Buffalo3</VehicleHash>
    <VehicleHash>Jester2</VehicleHash>
    <VehicleHash>Massacro2</VehicleHash>
  </AvailableVehicles>
  <LapsAvailable>true</LapsAvailable>
  <DecorativeProps />
  <Trigger>
    <X>1080.49438</X>
    <Y>-97.3724442</Y>
    <Z>81.19024</Z>
  </Trigger>
  <Name>Nascar</Name>
  <Description>Cool race!</Description>
</Race>