<?xml version="1.0" encoding="utf-8"?>
<Race xmlns:xsd="http://www.w3.org/2001/XMLSchema" xmlns:xsi="http://www.w3.org/2001/XMLSchema-instance">
  <Checkpoints>
    <Vector3>
      <X>1520.82935</X>
      <Y>3189.71826</Y>
      <Z>39.4629745</Z>
    </Vector3>
    <Vector3>
      <X>1758.49048</X>
      <Y>3269.555</Y>
      <Z>40.26471</Z>
    </Vector3>
    <Vector3>
      <X>1757.35376</X>
      <Y>3404.26978</Y>
      <Z>37.485054</Z>
    </Vector3>
    <Vector3>
      <X>1720.90771</X>
      <Y>3585.95728</Y>
      <Z>34.4154434</Z>
    </Vector3>
    <Vector3>
      <X>1944.62744</X>
      <Y>3713.797</Y>
      <Z>31.3824463</Z>
    </Vector3>
    <Vector3>
      <X>2003.91028</X>
      <Y>3825.15356</Y>
      <Z>31.288475</Z>
    </Vector3>
    <Vector3>
      <X>1866.96948</X>
      <Y>3948.03418</Y>
      <Z>32.08215</Z>
    </Vector3>
    <Vector3>
      <X>1667.4917</X>
      <Y>3861.666</Y>
      <Z>33.90805</Z>
    </Vector3>
    <Vector3>
      <X>1462.74512</X>
      <Y>3709.63</Y>
      <Z>33.02282</Z>
    </Vector3>
    <Vector3>
      <X>1220.89392</X>
      <Y>3628.52832</Y>
      <Z>32.6483078</Z>
    </Vector3>
    <Vector3>
      <X>932.508362</X>
      <Y>3633.618</Y>
      <Z>31.5049725</Z>
    </Vector3>
    <Vector3>
      <X>703.3632</X>
      <Y>3585.98584</Y>
      <Z>31.9791031</Z>
    </Vector3>
    <Vector3>
      <X>466.135925</X>
      <Y>3585.48169</Y>
      <Z>32.34855</Z>
    </Vector3>
    <Vector3>
      <X>410.115936</X>
      <Y>3540.63428</Y>
      <Z>32.99251</Z>
    </Vector3>
    <Vector3>
      <X>331.6488</X>
      <Y>3445.33374</Y>
      <Z>35.1524353</Z>
    </Vector3>
    <Vector3>
      <X>192.6795</X>
      <Y>3394.89966</Y>
      <Z>37.1299477</Z>
    </Vector3>
    <Vector3>
      <X>104.511139</X>
      <Y>3520.57666</Y>
      <Z>38.7777977</Z>
    </Vector3>
    <Vector3>
      <X>45.8596764</X>
      <Y>3594.16943</Y>
      <Z>38.7932167</Z>
    </Vector3>
    <Vector3>
      <X>-106.377975</X>
      <Y>3620.36865</Y>
      <Z>43.8333473</Z>
    </Vector3>
    <Vector3>
      <X>-282.282745</X>
      <Y>3959.835</Y>
      <Z>41.9901657</Z>
    </Vector3>
    <Vector3>
      <X>-529.706848</X>
      <Y>3956.53125</Y>
      <Z>92.17645</Z>
    </Vector3>
    <Vector3>
      <X>-782.7271</X>
      <Y>4051.29272</Y>
      <Z>155.363449</Z>
    </Vector3>
    <Vector3>
      <X>-907.7743</X>
      <Y>4109.615</Y>
      <Z>157.543518</Z>
    </Vector3>
    <Vector3>
      <X>-1037.24829</X>
      <Y>4212.526</Y>
      <Z>117.21582</Z>
    </Vector3>
    <Vector3>
      <X>-1187.28955</X>
      <Y>4290.605</Y>
      <Z>78.26116</Z>
    </Vector3>
    <Vector3>
      <X>-1323.867</X>
      <Y>4177.573</Y>
      <Z>62.129055</Z>
    </Vector3>
    <Vector3>
      <X>-1407.05066</X>
      <Y>4187.57129</Y>
      <Z>47.2449265</Z>
    </Vector3>
    <Vector3>
      <X>-1680.5282</X>
      <Y>4252.14355</Y>
      <Z>76.77363</Z>
    </Vector3>
    <Vector3>
      <X>-1815.27271</X>
      <Y>4388.574</Y>
      <Z>50.0491142</Z>
    </Vector3>
    <Vector3>
      <X>-1958.13416</X>
      <Y>4472.91943</Y>
      <Z>32.8387337</Z>
    </Vector3>
    <Vector3>
      <X>-2098.609</X>
      <Y>4511.61035</Y>
      <Z>27.8960724</Z>
    </Vector3>
    <Vector3>
      <X>-2201.74048</X>
      <Y>4481.344</Y>
      <Z>34.232254</Z>
    </Vector3>
    <Vector3>
      <X>-2256.17432</X>
      <Y>4322.99365</Y>
      <Z>44.06457</Z>
    </Vector3>
    <Vector3>
      <X>-2279.21045</X>
      <Y>4260.58447</Y>
      <Z>42.91684</Z>
    </Vector3>
    <Vector3>
      <X>-2301.80933</X>
      <Y>4276.20947</Y>
      <Z>34.8853226</Z>
    </Vector3>
    <Vector3>
      <X>-2340.4873</X>
      <Y>4253.914</Y>
      <Z>26.0073242</Z>
    </Vector3>
    <Vector3>
      <X>-2407.43066</X>
      <Y>4234.01953</Y>
      <Z>9.756945</Z>
    </Vector3>
    <Vector3>
      <X>-2481.82373</X>
      <Y>4070.07227</Y>
      <Z>6.44457054</Z>
    </Vector3>
    <Vector3>
      <X>-2503.85962</X>
      <Y>3833.65015</Y>
      <Z>8.854881</Z>
    </Vector3>
    <Vector3>
      <X>-2564.94873</X>
      <Y>3624.87573</Y>
      <Z>6.233267</Z>
    </Vector3>
    <Vector3>
      <X>-2582.946</X>
      <Y>3552.879</Y>
      <Z>8.186427</Z>
    </Vector3>
  </Checkpoints>
  <SpawnPoints>
    <SpawnPoint>
      <Position>
        <X>1050.64417</X>
        <Y>3079.96582</Y>
        <Z>41.8069153</Z>
      </Position>
      <Heading>-78.67469</Heading>
    </SpawnPoint>
    <SpawnPoint>
      <Position>
        <X>1052.097</X>
        <Y>3074.26587</Y>
        <Z>41.8090935</Z>
      </Position>
      <Heading>-75.3036346</Heading>
    </SpawnPoint>
    <SpawnPoint>
      <Position>
        <X>1053.35767</X>
        <Y>3069.13281</Y>
        <Z>41.81539</Z>
      </Position>
      <Heading>-71.6348953</Heading>
    </SpawnPoint>
    <SpawnPoint>
      <Position>
        <X>1054.71533</X>
        <Y>3063.60767</Y>
        <Z>41.8223534</Z>
      </Position>
      <Heading>-73.70123</Heading>
    </SpawnPoint>
    <SpawnPoint>
      <Position>
        <X>1056.10352</X>
        <Y>3058.45386</Y>
        <Z>41.8263931</Z>
      </Position>
      <Heading>-74.05787</Heading>
    </SpawnPoint>
    <SpawnPoint>
      <Position>
        <X>1057.504</X>
        <Y>3052.7312</Y>
        <Z>41.8388252</Z>
      </Position>
      <Heading>-73.12535</Heading>
    </SpawnPoint>
    <SpawnPoint>
      <Position>
        <X>1058.81384</X>
        <Y>3047.54956</Y>
        <Z>41.84701</Z>
      </Position>
      <Heading>-75.4500351</Heading>
    </SpawnPoint>
    <SpawnPoint>
      <Position>
        <X>1060.12793</X>
        <Y>3042.67432</Y>
        <Z>41.84673</Z>
      </Position>
      <Heading>-76.10249</Heading>
    </SpawnPoint>
    <SpawnPoint>
      <Position>
        <X>1061.82544</X>
        <Y>3037.27319</Y>
        <Z>41.8459549</Z>
      </Position>
      <Heading>-75.13185</Heading>
    </SpawnPoint>
    <SpawnPoint>
      <Position>
        <X>1063.27466</X>
        <Y>3032.15381</Y>
        <Z>41.8450127</Z>
      </Position>
      <Heading>-74.3482742</Heading>
    </SpawnPoint>
    <SpawnPoint>
      <Position>
        <X>1064.75842</X>
        <Y>3026.59717</Y>
        <Z>41.8472939</Z>
      </Position>
      <Heading>-73.83697</Heading>
    </SpawnPoint>
    <SpawnPoint>
      <Position>
        <X>1066.11682</X>
        <Y>3021.06274</Y>
        <Z>41.86055</Z>
      </Position>
      <Heading>-74.6581039</Heading>
    </SpawnPoint>
    <SpawnPoint>
      <Position>
        <X>1067.51074</X>
        <Y>3015.50854</Y>
        <Z>41.86785</Z>
      </Position>
      <Heading>-74.45369</Heading>
    </SpawnPoint>
    <SpawnPoint>
      <Position>
        <X>1068.73584</X>
        <Y>3010.091</Y>
        <Z>41.8809433</Z>
      </Position>
      <Heading>-75.67102</Heading>
    </SpawnPoint>
    <SpawnPoint>
      <Position>
        <X>1070.34058</X>
        <Y>3004.4624</Y>
        <Z>41.893425</Z>
      </Position>
      <Heading>-74.01468</Heading>
    </SpawnPoint>
    <SpawnPoint>
      <Position>
        <X>1049.062</X>
        <Y>3085.37183</Y>
        <Z>41.8445</Z>
      </Position>
      <Heading>-74.61689</Heading>
    </SpawnPoint>
  </SpawnPoints>
  <AvailableVehicles>
    <VehicleHash>Hauler</VehicleHash>
  </AvailableVehicles>
  <LapsAvailable>true</LapsAvailable>
  <DecorativeProps />
  <Trigger>
    <X>1046.33374</X>
    <Y>3053.59351</Y>
    <Z>40.9734</Z>
  </Trigger>
  <Name>Truck</Name>
  <Description>Cool race!</Description>
</Race>